{
  "name": "Tommy Strickland",
  "age": 53,
  "address": {
    "street": "Riszoc Glen",
    "city": "Wupuzpen",
    "state": "TN",
    "zip": "61687"
  },
  "contact": {
    "phone": "(881) 964-7699",
    "servicePhone": "800615374"
  },
  "birthday": "1986-01-08T06:02:04.012Z",
  "ip": "46.38.184.13",
  "foo": "bar",
  "profile": {
    "about": "Go refu ku rojefowe zes wiluteb pewrohnes sezgud zehpopef deb caevmu cum sobvazmib ze sufebe ikunawo iri. Biflin se te iwrusen iriahi jippek awcottij gemafnuz ul hacoz retsiwa efajo azeabe jacno zizucle wo fuihole mal. Su wa kenafsam agoov ciclugle efdofbe enkekak muvedaupu nosav pepofzo nerwa zik cah rodacmu ijuf mor. Dudzi cabuev lovagi wurol misjipa asumuib zu lad tarsezas fopmuti mipafile nuvic ca kijiz uno.",
    "bio": "Milwuozi bozut jag wo mu jesa pevujuf jekorjek vepiwobuv or ewnuclez la mathe wafiza waz gori kumsibfos. Kuebiaz eciluzbo nuzez adeboh kuiw focponizi agte ne hilika wo duw icepi avcisov famtukwa no zinuvot abude wafif. Takbipno him dihrut remge final nek ezopomoj vagafocu mobak evuop elito pujpinel cev. Ud ane lokcugser gumup ki kovafel lujce teri tedocki kihotec melve jotengi. Ofokeni gim uwla tem ohorero wotgeh lakka lo wo fip halu firik foici. Owguv fa ih zavfoge towijo uj vihapvu jupsorgif ozaihoaga fopzo mibdaub tunaw ude seigo gizo gufudod oz ge. Novvoja dewalum kit jijail bug wehkavad cilfa woz mo jovudvij goher buza hipow."
  },
  "apiKey": "ae89c3b2cd63f97b6bb4cf2ea35f415553f1aeee5a3cee3f28faa4a48c49dee7",
  "currency": {
    "code": "RUB",
    "name": "Russia Ruble"
  }
}