{
  "name": "Helena Manning",
  "age": 48,
  "address": {
    "street": "Tola Parkway",
    "city": "Tucepodi",
    "state": "LA",
    "zip": "78244"
  },
  "contact": {
    "phone": "(861) 963-3559",
    "servicePhone": "800947792"
  },
  "birthday": "1993-03-15T00:25:34.147Z",
  "ip": "145.143.251.27",
  "foo": "bar",
  "profile": {
    "about": "Ce so nodfik iwu san fuccoptu urhib ro nobcemik tal soope tezi bes gobgu. Kubeus mid dudajkiv capauki baktu gig worut hu pucvalba fuhluw ab bujecogu gok. Sudaj pa zitu cu ludgegmiz gijo pipwi eci mabbojupi ercaju abinukfo meigo cuw omvosa fativ.",
    "bio": "Ruwef fazije ge bekab sope mijij vipjef uki bali tududka itejokde kut anko. Jifpokiz bu ucuva mamuhe mo owaf tezitzam zoculifu mej mucuz podvuliv lub lamdic. Oshuklaf meggop gi si re fijtu ri vot rigbep tamkofe dewad wo ge. Mued dahaz temjued wuv ebigo ceguwege efhem ceropi rejirove go dag isavatnud zuw ipge vir. Ace vohvota cudta fuiprin lopsam dowfawhos pepikoc vuhovkof mal nukibuco gaw gisgo losurevi wotjis vudef. Et cetpitok fumhapow pietpe vaoga gecib tosobel mog von voupeben ebiva ame. Domezgac zerlohbuw da cipenu todjial hemog tikviuzi omina nupruw vufezirom si hum zucaij em akdige."
  },
  "apiKey": "f91949542743de7bc468328e1f08f13831acf1b27753a0f43f86a1a171cf0fcb",
  "currency": {
    "code": "BSD",
    "name": "Bahamas Dollar"
  }
}